los_client/__about__.py
los_client/__init__.py
los_client/cli.py
los_client/client.py
los_client/config.py
los_client/exceptions.py
los_client/models.py
los_client/py.typed
los_client/run_solver.py
los_client-0.4.0.dist-info/METADATA
los_client-0.4.0.dist-info/WHEEL
los_client-0.4.0.dist-info/entry_points.txt
los_client-0.4.0.dist-info/licenses/LICENSE
los_client-0.4.0.dist-info/RECORD
