Metadata-Version: 2.4
Name: los-client
Version: 0.4.0
Summary: League of Solvers Client CLI
Project-URL: Homepage, https://los.npify.com
Project-URL: Bug Reports, https://github.com/NPify/los_client/issues
Project-URL: Source, https://github.com/NPify/los_client
Author-email: Stephan Gocht <stephan@drgocht.com>, Amr Yonis <amrmohamedyonis@gmail.com>
License-Expression: MIT
License-File: LICENSE
Classifier: Development Status :: 4 - Beta
Classifier: License :: OSI Approved :: MIT License
Requires-Python: >=3.11
Requires-Dist: pyaes>=1.6.1
Requires-Dist: pydantic>=2.10.3
Requires-Dist: websockets>=14.1
